CoffeePaginator/CoffeePaginator.py
CoffeePaginator/__init__.py
CoffeePaginator-1.1a0.dist-info/LICENSE
CoffeePaginator-1.1a0.dist-info/METADATA
CoffeePaginator-1.1a0.dist-info/WHEEL
CoffeePaginator-1.1a0.dist-info/top_level.txt
CoffeePaginator-1.1a0.dist-info/RECORD
