Metadata-Version: 2.1
Name: CoffeePaginator
Version: 1.1a0
Summary: Простой модуль для создания страниц на Disnake
Home-page: https://github.com/Sha4ek/CoffeePaginator
Author: Sha4ek
License: UNKNOWN
Platform: UNKNOWN
Classifier: Programming Language :: Python :: 3.8
Classifier: License :: OSI Approved :: MIT License
Classifier: Operating System :: OS Independent
Requires-Python: >=3.8
Requires-Dist: disnake (>=2.1.2)
